<?xml version="1.0" encoding="UTF-8"?><record_update table="sp_instance">
    <sp_instance action="INSERT_OR_UPDATE">
        <active>true</active>
        <class_name/>
        <color>default</color>
        <css/>
        <glyph/>
        <id/>
        <order>1</order>
        <roles/>
        <short_description/>
        <size>md</size>
        <sp_column display_value="1">7239afd1139c7f401f2f53173244b036</sp_column>
        <sp_widget display_value="send slacker chat">3e39abd1139c7f401f2f53173244b0a1</sp_widget>
        <sys_class_name>sp_instance</sys_class_name>
        <sys_created_by>admin-eduque</sys_created_by>
        <sys_created_on>2019-03-19 15:14:24</sys_created_on>
        <sys_customer_update>false</sys_customer_update>
        <sys_id>7e39afd1139c7f401f2f53173244b037</sys_id>
        <sys_mod_count>0</sys_mod_count>
        <sys_name/>
        <sys_package display_value="SlackOff" source="x_165574_slackoff">33504e2b4f2467000d952b8ca310c7d1</sys_package>
        <sys_policy/>
        <sys_replace_on_upgrade>false</sys_replace_on_upgrade>
        <sys_scope display_value="SlackOff">33504e2b4f2467000d952b8ca310c7d1</sys_scope>
        <sys_update_name>sp_instance_7e39afd1139c7f401f2f53173244b037</sys_update_name>
        <sys_updated_by>admin-eduque</sys_updated_by>
        <sys_updated_on>2019-03-19 15:14:24</sys_updated_on>
        <title/>
        <url/>
        <widget_parameters/>
    </sp_instance>
    <sys_translated_text action="delete_multiple" query="documentkey=7e39afd1139c7f401f2f53173244b037"/>
</record_update>
